{
	"configurations" : 
	[
		{
			"directories" : 
			[
				{
					"build" : ".",
					"jsonFile" : "directory-.-Debug-f5ebdc15457944623624.json",
					"projectIndex" : 0,
					"source" : ".",
					"targetIndexes" : 
					[
						0
					]
				}
			],
			"name" : "Debug",
			"projects" : 
			[
				{
					"directoryIndexes" : 
					[
						0
					],
					"name" : "HelloWorld",
					"targetIndexes" : 
					[
						0
					]
				}
			],
			"targets" : 
			[
				{
					"directoryIndex" : 0,
					"id" : "helloWorld::@6890427a1f51a3e7e1df",
					"jsonFile" : "target-helloWorld-Debug-24e7190de98688934c9e.json",
					"name" : "helloWorld",
					"projectIndex" : 0
				}
			]
		}
	],
	"kind" : "codemodel",
	"paths" : 
	{
		"build" : "/Users/shaystevens/Desktop/COSC342/Lab01/HelloWorld/build",
		"source" : "/Users/shaystevens/Desktop/COSC342/Lab01/HelloWorld"
	},
	"version" : 
	{
		"major" : 2,
		"minor" : 3
	}
}
